alie/VERSION
alie/__init__.py
alie/__main__.py
alie/cli.py
alie/data/README.md
alie-0.2.1.dist-info/METADATA
alie-0.2.1.dist-info/RECORD
alie-0.2.1.dist-info/WHEEL
alie-0.2.1.dist-info/entry_points.txt
alie-0.2.1.dist-info/top_level.txt
