Metadata-Version: 2.1
Name: alie
Version: 0.2.1
Summary: 👟 register aliases with ease.
Home-page: https://github.com/jsmedmar/alie
Author: Juan S. Medina
License: BSD
Platform: UNKNOWN
Classifier: Intended Audience :: Developers
Classifier: Intended Audience :: Science/Research
Classifier: License :: OSI Approved :: MIT License
Classifier: Natural Language :: English
Classifier: Operating System :: Unix
Classifier: Operating System :: POSIX
Classifier: Programming Language :: Python :: 2 :: Only
Classifier: Topic :: Utilities
Provides-Extra: test
Requires-Dist: Click (>=6.7)
Requires-Dist: python-slugify (>=1.0.22)
Provides-Extra: test
Requires-Dist: coverage (>=4.4.2); extra == 'test'
Requires-Dist: pydocstyle (>=2.1.1); extra == 'test'
Requires-Dist: pytest-cov (>=2.5.1); extra == 'test'
Requires-Dist: pytest-env (==0.6.2); extra == 'test'
Requires-Dist: pytest-sugar (>=0.9.1); extra == 'test'
Requires-Dist: pylint (>=1.8.1); extra == 'test'
Requires-Dist: tox (==2.9.1); extra == 'test'
